{
  "fundamentals": {
    "00631L": {
      "pe": null,
      "fpe": null,
      "peg": null,
      "ps": null,
      "pb": null,
      "rev_yoy": null,
      "rev_fwd": null,
      "hist_avg_pe": null,
      "eps_ttm": null,
      "eps_cur_q": null,
      "eps_next_q2": null,
      "eps_cur_y": null,
      "eps_next_y": null,
      "fetched_at": 1780767358733
    }
  },
  "macro": {
    "results": [
      {
        "symbol": "^GSPC",
        "name": "S&P 500",
        "cat": "股市",
        "price": 7383.740234375,
        "chg1d": -2.6445361894386843,
        "chg7d": -2.5899507748118182
      },
      {
        "symbol": "^IXIC",
        "name": "Nasdaq",
        "cat": "股市",
        "price": 25709.4296875,
        "chg1d": -4.179989127532529,
        "chg7d": -4.683228745933828
      },
      {
        "symbol": "^SOX",
        "name": "費城半導體",
        "cat": "股市",
        "price": 12220.759765625,
        "chg1d": -10.256950500275382,
        "chg7d": -4.743955847802647
      },
      {
        "symbol": "^VIX",
        "name": "恐慌指數 VIX",
        "cat": "情緒",
        "price": 21.510000228881836,
        "chg1d": 39.675329621434635,
        "chg7d": 40.40470402978452
      },
      {
        "symbol": "^TNX",
        "name": "10年期美債殖利率",
        "cat": "利率",
        "price": 4.535999774932861,
        "chg1d": 1.3178363927808754,
        "chg7d": 1.863905344452466
      },
      {
        "symbol": "DX-Y.NYB",
        "name": "美元指數",
        "cat": "外匯",
        "price": 100.06999969482422,
        "chg1d": 0.6639130956660497,
        "chg7d": 0.8770189247444807
      },
      {
        "symbol": "GC=F",
        "name": "黃金",
        "cat": "商品",
        "price": 4365.2998046875,
        "chg1d": -2.4688324952396994,
        "chg7d": -4.280236713353799
      },
      {
        "symbol": "CL=F",
        "name": "原油 (WTI)",
        "cat": "商品",
        "price": 90.54000091552734,
        "chg1d": -2.687016310618692,
        "chg7d": 3.640110214009056
      },
      {
        "symbol": "BTC-USD",
        "name": "Bitcoin",
        "cat": "加密",
        "price": 61717.328125,
        "chg1d": 1.3963367354941176,
        "chg7d": -16.12178547917861
      }
    ],
    "news": [
      {
        "uuid": "d7be79ec-de13-3098-b19e-61a4c77d9d6c",
        "title": "After Shares Surged 84% in a Month, Micron's CEO Just Sold $38 Million of Stock. Should Investors Be Worried?",
        "publisher": "Motley Fool",
        "link": "https://finance.yahoo.com/m/d7be79ec-de13-3098-b19e-61a4c77d9d6c/after-shares-surged-84%25-in-a.html",
        "providerPublishTime": 1780844700,
        "type": "STORY",
        "thumbnail": {
          "resolutions": [
            {
              "url": "https://s.yimg.com/uu/api/res/1.2/Eqrp6k1lX_f3x6lv1xOcZg--~B/aD04NDA7dz0xNDAwO2FwcGlkPXl0YWNoeW9u/https://media.zenfs.com/en/motleyfool.com/9712c7b8c6b85f34d0b47297c7ef65a2",
              "width": 1400,
              "height": 840,
              "tag": "original"
            },
            {
              "url": "https://s.yimg.com/uu/api/res/1.2/z7sRQ4b7w.ZWKxqSf5KLcQ--~B/Zmk9ZmlsbDtoPTE0MDtweW9mZj0wO3c9MTQwO2FwcGlkPXl0YWNoeW9u/https://media.zenfs.com/en/motleyfool.com/9712c7b8c6b85f34d0b47297c7ef65a2",
              "width": 140,
              "height": 140,
              "tag": "140x140"
            }
          ]
        },
        "relatedTickers": [
          "MU",
          "NVDA"
        ],
        "_sym": "MU",
        "titleZh": "股價在一個月內飆升84%後，美光的首席執行官剛剛賣出了3800萬$的股票。投資者應該擔心嗎？"
      },
      {
        "uuid": "83475878-687c-36f7-a452-50a8d5d79238",
        "title": "Is Harmonic Inc. (HLIT) A Good Stock To Buy Now?",
        "publisher": "Insider Monkey",
        "link": "https://finance.yahoo.com/markets/stocks/articles/harmonic-inc-hlit-good-stock-145254183.html",
        "providerPublishTime": 1780843974,
        "type": "STORY",
        "thumbnail": {
          "resolutions": [
            {
              "url": "https://s.yimg.com/uu/api/res/1.2/1N5B_IamuGoDgNaoqLIMGg--~B/aD02Njc7dz0xMDAwO2FwcGlkPXl0YWNoeW9u/https://media.zenfs.com/en/insidermonkey.com/15f3588c490ebe61c410c45a1e685440",
              "width": 1000,
              "height": 667,
              "tag": "original"
            },
            {
              "url": "https://s.yimg.com/uu/api/res/1.2/UZzV4BaKfhXCSQRCimgBWA--~B/Zmk9ZmlsbDtoPTE0MDtweW9mZj0wO3c9MTQwO2FwcGlkPXl0YWNoeW9u/https://media.zenfs.com/en/insidermonkey.com/15f3588c490ebe61c410c45a1e685440",
              "width": 140,
              "height": 140,
              "tag": "140x140"
            }
          ]
        },
        "relatedTickers": [
          "HLIT",
          "NVDA",
          "NOK",
          "CMCSA",
          "CHTR"
        ],
        "_sym": "NVDA",
        "titleZh": "Harmonic Inc. （ HLIT ）是現在購買的好股票嗎？"
      },
      {
        "uuid": "074ab26d-1294-3dc1-bd5d-e8c86d7af559",
        "title": "Is Nokia Oyj (NOK) A Good Stock To Buy Now?",
        "publisher": "Insider Monkey",
        "link": "https://finance.yahoo.com/markets/stocks/articles/nokia-oyj-nok-good-stock-145002052.html",
        "providerPublishTime": 1780843802,
        "type": "STORY",
        "thumbnail": {
          "resolutions": [
            {
              "url": "https://s.yimg.com/uu/api/res/1.2/xRSave_qbELSgFNYCZOokA--~B/aD01OTI7dz04MDA7YXBwaWQ9eXRhY2h5b24-/https://media.zenfs.com/en/insidermonkey.com/ca4b089cab28a90d201d959e4353350b",
              "width": 800,
              "height": 592,
              "tag": "original"
            },
            {
              "url": "https://s.yimg.com/uu/api/res/1.2/vMJQbeCKkLPgByU1C3qnlQ--~B/Zmk9ZmlsbDtoPTE0MDtweW9mZj0wO3c9MTQwO2FwcGlkPXl0YWNoeW9u/https://media.zenfs.com/en/insidermonkey.com/ca4b089cab28a90d201d959e4353350b",
              "width": 140,
              "height": 140,
              "tag": "140x140"
            }
          ]
        },
        "relatedTickers": [
          "NOK",
          "NVDA"
        ],
        "_sym": "NVDA",
        "titleZh": "Nokia Oyj (NOK)是現在買進的好股票嗎？"
      },
      {
        "uuid": "d4f46c07-7a62-38d2-b8cb-d4564857a31c",
        "title": "Is AECOM (ACM) A Good Stock To Buy Now?",
        "publisher": "Insider Monkey",
        "link": "https://finance.yahoo.com/markets/stocks/articles/aecom-acm-good-stock-buy-144643137.html",
        "providerPublishTime": 1780843603,
        "type": "STORY",
        "thumbnail": {
          "resolutions": [
            {
              "url": "https://s.yimg.com/uu/api/res/1.2/6OKl0oE5mY29JECspNhNVQ--~B/aD01MDA7dz03NTA7YXBwaWQ9eXRhY2h5b24-/https://media.zenfs.com/en/insidermonkey.com/00705ac839e6239e6299815cd518b32a",
              "width": 750,
              "height": 500,
              "tag": "original"
            },
            {
              "url": "https://s.yimg.com/uu/api/res/1.2/qSawGk5UEd3lADjKNUsV1Q--~B/Zmk9ZmlsbDtoPTE0MDtweW9mZj0wO3c9MTQwO2FwcGlkPXl0YWNoeW9u/https://media.zenfs.com/en/insidermonkey.com/00705ac839e6239e6299815cd518b32a",
              "width": 140,
              "height": 140,
              "tag": "140x140"
            }
          ]
        },
        "relatedTickers": [
          "ACM",
          "MSFT",
          "GOOG",
          "AMZN",
          "META"
        ],
        "_sym": "GOOGL",
        "titleZh": "AECOM （ ACM ）是現在購買的好股票嗎？"
      },
      {
        "uuid": "77b3e6f1-0cc1-35ba-a322-8bdeb775f570",
        "title": "1 Cash-Rich Industrial Titan Under $40 to Buy Hand Over Fist to Capitalize on the New Trump Tariff Supercycle",
        "publisher": "24/7 Wall St.",
        "link": "https://finance.yahoo.com/m/77b3e6f1-0cc1-35ba-a322-8bdeb775f570/1-cash-rich-industrial-titan.html",
        "providerPublishTime": 1780843219,
        "type": "STORY",
        "thumbnail": {
          "resolutions": [
            {
              "url": "https://s.yimg.com/uu/api/res/1.2/hxzMhEKc1tjRjPmx1yJ6Bw--~B/aD01NTA7dz05MDA7YXBwaWQ9eXRhY2h5b24-/https://media.zenfs.com/en/24_7_wall_st__718/26481712f19c2d34aa51eb4808e29788",
              "width": 900,
              "height": 550,
              "tag": "original"
            },
            {
              "url": "https://s.yimg.com/uu/api/res/1.2/Mr9SJRXzJtDNiLRUVFrtNA--~B/Zmk9ZmlsbDtoPTE0MDtweW9mZj0wO3c9MTQwO2FwcGlkPXl0YWNoeW9u/https://media.zenfs.com/en/24_7_wall_st__718/26481712f19c2d34aa51eb4808e29788",
              "width": 140,
              "height": 140,
              "tag": "140x140"
            }
          ]
        },
        "relatedTickers": [
          "CLF",
          "NVDA"
        ],
        "_sym": "NVDA",
        "titleZh": "1現金充裕的$ 40以下工業巨頭購買Hand Over Fist以利用新的特朗普關稅超級循環"
      },
      {
        "uuid": "31f1b90c-d8e8-3e99-9769-965ccf07327f",
        "title": "How to Turn Your 2025 Tax Return Into a Retirement Planning Checkup",
        "publisher": "Motley Fool",
        "link": "https://finance.yahoo.com/m/31f1b90c-d8e8-3e99-9769-965ccf07327f/how-to-turn-your-2025-tax.html",
        "providerPublishTime": 1780842900,
        "type": "STORY",
        "thumbnail": {
          "resolutions": [
            {
              "url": "https://s.yimg.com/uu/api/res/1.2/CHfVmEt7cA8lX6mJRL38KA--~B/aD04MDA7dz0xMjgwO2FwcGlkPXl0YWNoeW9u/https://media.zenfs.com/en/motleyfool.com/54f3903d9e4ef4a2dd13a4aaba454556",
              "width": 1280,
              "height": 800,
              "tag": "original"
            },
            {
              "url": "https://s.yimg.com/uu/api/res/1.2/VcuG3yqOKdMSf9t1DKtLWg--~B/Zmk9ZmlsbDtoPTE0MDtweW9mZj0wO3c9MTQwO2FwcGlkPXl0YWNoeW9u/https://media.zenfs.com/en/motleyfool.com/54f3903d9e4ef4a2dd13a4aaba454556",
              "width": 140,
              "height": 140,
              "tag": "140x140"
            }
          ]
        },
        "relatedTickers": [
          "NVDA"
        ],
        "_sym": "NVDA",
        "titleZh": "如何將2025年的報稅表轉化為退休計劃檢查"
      },
      {
        "uuid": "0bf523bd-f9d4-39da-9f98-85437fa89e4e",
        "title": "Alphabet Weighs SpaceX AI Deal And $85b Raise Against Valuation Concerns",
        "publisher": "Simply Wall St.",
        "link": "https://finance.yahoo.com/markets/stocks/articles/alphabet-weighs-spacex-ai-deal-141246480.html",
        "providerPublishTime": 1780841566,
        "type": "STORY",
        "thumbnail": {
          "resolutions": [
            {
              "url": "https://s.yimg.com/uu/api/res/1.2/VTfDtc_pApg1_vVDy_b8eQ--~B/aD00MzI7dz0xMTk0O2FwcGlkPXl0YWNoeW9u/https://media.zenfs.com/en/simply_wall_st__316/1fc7d8c4b041b0aaed5c1d373b17b5b4",
              "width": 1194,
              "height": 432,
              "tag": "original"
            },
            {
              "url": "https://s.yimg.com/uu/api/res/1.2/Kv5RbP0mE9EpcenlZ1w2hg--~B/Zmk9ZmlsbDtoPTE0MDtweW9mZj0wO3c9MTQwO2FwcGlkPXl0YWNoeW9u/https://media.zenfs.com/en/simply_wall_st__316/1fc7d8c4b041b0aaed5c1d373b17b5b4",
              "width": 140,
              "height": 140,
              "tag": "140x140"
            }
          ]
        },
        "relatedTickers": [
          "GOOG",
          "SPAX.PVT",
          "BRK-B",
          "NVDA"
        ],
        "_sym": "GOOGL",
        "titleZh": "Alphabet權衡SpaceX AI交易和$ 85B的籌資，反對估值擔憂"
      },
      {
        "uuid": "c3581aa2-b4e0-3475-92da-e6766db014fc",
        "title": "WWDC 2026 Puts Apple’s AI Pivot And Services Valuation In Focus",
        "publisher": "Simply Wall St.",
        "link": "https://finance.yahoo.com/markets/stocks/articles/wwdc-2026-puts-apple-ai-141211200.html",
        "providerPublishTime": 1780841531,
        "type": "STORY",
        "thumbnail": {
          "resolutions": [
            {
              "url": "https://s.yimg.com/uu/api/res/1.2/fBnY8upz5XxbZDDWlufZ9w--~B/aD00MzI7dz0xMTk0O2FwcGlkPXl0YWNoeW9u/https://media.zenfs.com/en/simply_wall_st__316/69084628647944e382f8e555f97913e8",
              "width": 1194,
              "height": 432,
              "tag": "original"
            },
            {
              "url": "https://s.yimg.com/uu/api/res/1.2/foN3eFZWC9tLTJfgfqJIuQ--~B/Zmk9ZmlsbDtoPTE0MDtweW9mZj0wO3c9MTQwO2FwcGlkPXl0YWNoeW9u/https://media.zenfs.com/en/simply_wall_st__316/69084628647944e382f8e555f97913e8",
              "width": 140,
              "height": 140,
              "tag": "140x140"
            }
          ]
        },
        "relatedTickers": [
          "AAPL",
          "GOOG",
          "NVDA"
        ],
        "_sym": "GOOGL",
        "titleZh": "WWDC 2026聚焦蘋果的AI樞紐和服務估值"
      },
      {
        "uuid": "4e57fd62-a165-35ac-ab25-3c8bcc828d3c",
        "title": "Dow Jones Futures Due Amid Market Rally's First Real Test; SpaceX IPO, Apple, Oracle Ahead",
        "publisher": "Investor's Business Daily",
        "link": "https://finance.yahoo.com/m/4e57fd62-a165-35ac-ab25-3c8bcc828d3c/dow-jones-futures-due-amid.html",
        "providerPublishTime": 1780840764,
        "type": "STORY",
        "thumbnail": {
          "resolutions": [
            {
              "url": "https://s.yimg.com/uu/api/res/1.2/wxSpaDxF_Oj8ztWDCK2k1g--~B/aD01NjM7dz0xMDAwO2FwcGlkPXl0YWNoeW9u/https://media.zenfs.com/en/ibd.com/53cb5ccd6529d26f805783b37decf65d",
              "width": 1000,
              "height": 563,
              "tag": "original"
            },
            {
              "url": "https://s.yimg.com/uu/api/res/1.2/j2lwzAncEZN7p0leSv8hdw--~B/Zmk9ZmlsbDtoPTE0MDtweW9mZj0wO3c9MTQwO2FwcGlkPXl0YWNoeW9u/https://media.zenfs.com/en/ibd.com/53cb5ccd6529d26f805783b37decf65d",
              "width": 140,
              "height": 140,
              "tag": "140x140"
            }
          ]
        },
        "relatedTickers": [
          "^DJI",
          "SPAX.PVT",
          "ORCL",
          "AAPL",
          "^GSPC",
          "ORCL-PD",
          "SPCX",
          "LLY",
          "^IXIC",
          "GOOG",
          "AVGO",
          "CIEN"
        ],
        "_sym": "GOOGL",
        "titleZh": "道瓊斯期貨因應市場反彈的首次真正考驗； SpaceX IPO、蘋果、甲骨文未來"
      },
      {
        "uuid": "76be55b2-dc43-3d0c-a3cc-6d947f1f2fc8",
        "title": "Here Are 5 AI-Related Stocks to Buy and Hold for the Next 5 Years",
        "publisher": "Motley Fool",
        "link": "https://finance.yahoo.com/m/76be55b2-dc43-3d0c-a3cc-6d947f1f2fc8/here-are-5-ai-related-stocks.html",
        "providerPublishTime": 1780840200,
        "type": "STORY",
        "thumbnail": {
          "resolutions": [
            {
              "url": "https://s.yimg.com/uu/api/res/1.2/UpDMz1.649TpRTkluYVG8Q--~B/aD03NTc7dz0xNDAwO2FwcGlkPXl0YWNoeW9u/https://media.zenfs.com/en/motleyfool.com/343e4ee8a6683475e45824adf58c1c91",
              "width": 1400,
              "height": 757,
              "tag": "original"
            },
            {
              "url": "https://s.yimg.com/uu/api/res/1.2/L3UiQvCdVEJx5ecbus7scg--~B/Zmk9ZmlsbDtoPTE0MDtweW9mZj0wO3c9MTQwO2FwcGlkPXl0YWNoeW9u/https://media.zenfs.com/en/motleyfool.com/343e4ee8a6683475e45824adf58c1c91",
              "width": 140,
              "height": 140,
              "tag": "140x140"
            }
          ]
        },
        "relatedTickers": [
          "INTC",
          "META",
          "MSFT",
          "AMZN",
          "GOOG",
          "NVDA"
        ],
        "_sym": "GOOGL",
        "titleZh": "以下是未來5年購買和持有的5隻AI相關股票"
      },
      {
        "uuid": "a962a53a-1d8d-3df1-9776-ed3c68627089",
        "title": "Why Marvell Technology Rallied in May",
        "publisher": "Motley Fool",
        "link": "https://finance.yahoo.com/m/a962a53a-1d8d-3df1-9776-ed3c68627089/why-marvell-technology.html",
        "providerPublishTime": 1780836000,
        "type": "STORY",
        "thumbnail": {
          "resolutions": [
            {
              "url": "https://s.yimg.com/uu/api/res/1.2/XdFJHHHNAuk97Fwqw5xXaw--~B/aD04OTI7dz0xNDAwO2FwcGlkPXl0YWNoeW9u/https://media.zenfs.com/en/motleyfool.com/9bdf2dacdfd5186860622dec6ece4eaa",
              "width": 1400,
              "height": 892,
              "tag": "original"
            },
            {
              "url": "https://s.yimg.com/uu/api/res/1.2/Oo1g1CJoA9AS_aE7FB6FcQ--~B/Zmk9ZmlsbDtoPTE0MDtweW9mZj0wO3c9MTQwO2FwcGlkPXl0YWNoeW9u/https://media.zenfs.com/en/motleyfool.com/9bdf2dacdfd5186860622dec6ece4eaa",
              "width": 140,
              "height": 140,
              "tag": "140x140"
            }
          ]
        },
        "relatedTickers": [
          "MRVL",
          "AMD",
          "NVDA",
          "INTC"
        ],
        "_sym": "AMD",
        "titleZh": "爲什麼Marvell Technology在5月份集會"
      },
      {
        "uuid": "dc6d5fc5-bb0c-4fdc-99f5-309ec954b1b5",
        "title": "AI stock mania is taking over the markets in 2026",
        "publisher": "Yahoo Finance",
        "link": "https://finance.yahoo.com/markets/article/ai-stock-mania-is-taking-over-the-markets-in-2026-123000964.html",
        "providerPublishTime": 1780835400,
        "type": "STORY",
        "thumbnail": {
          "resolutions": [
            {
              "url": "https://s.yimg.com/uu/api/res/1.2/iu8qDSZOEooI60uI6uHNag--~B/aD0zOTk5O3c9NjAwMDthcHBpZD15dGFjaHlvbg--/https://d29szjachogqwa.cloudfront.net/images/2026-06/7806654d-63ff-4cfb-8f0a-2fe1ac08c92c",
              "width": 6000,
              "height": 3999,
              "tag": "original"
            },
            {
              "url": "https://s.yimg.com/uu/api/res/1.2/QCNK0qzmXRV9xWrYZa2s.Q--~B/Zmk9ZmlsbDtoPTE0MDtweW9mZj0wO3c9MTQwO2FwcGlkPXl0YWNoeW9u/https://d29szjachogqwa.cloudfront.net/images/2026-06/7806654d-63ff-4cfb-8f0a-2fe1ac08c92c",
              "width": 140,
              "height": 140,
              "tag": "140x140"
            }
          ]
        },
        "relatedTickers": [
          "IBM",
          "NVDA",
          "AMD",
          "ARM",
          "HPE",
          "NOW",
          "INTC"
        ],
        "_sym": "AMD",
        "titleZh": "AI股票狂熱將在2026年接管市場"
      },
      {
        "uuid": "112d6e38-71e7-340b-8c72-a4bb2beca465",
        "title": "Prediction: Micron Technology Stock Could Go Parabolic After June 24. Here's Why.",
        "publisher": "Motley Fool",
        "link": "https://finance.yahoo.com/m/112d6e38-71e7-340b-8c72-a4bb2beca465/prediction%3A-micron-technology.html",
        "providerPublishTime": 1780830120,
        "type": "STORY",
        "thumbnail": {
          "resolutions": [
            {
              "url": "https://s.yimg.com/uu/api/res/1.2/cdrZZqDcKcIZd3pzeenCbw--~B/aD04NDA7dz0xNDAwO2FwcGlkPXl0YWNoeW9u/https://media.zenfs.com/en/motleyfool.com/babce0a5002b75a33cf40d19d2a90531",
              "width": 1400,
              "height": 840,
              "tag": "original"
            },
            {
              "url": "https://s.yimg.com/uu/api/res/1.2/52.ZZrnleAm5zEqfqMBKww--~B/Zmk9ZmlsbDtoPTE0MDtweW9mZj0wO3c9MTQwO2FwcGlkPXl0YWNoeW9u/https://media.zenfs.com/en/motleyfool.com/babce0a5002b75a33cf40d19d2a90531",
              "width": 140,
              "height": 140,
              "tag": "140x140"
            }
          ]
        },
        "relatedTickers": [
          "MU",
          "NVDA",
          "INTC"
        ],
        "_sym": "MU",
        "titleZh": "預測： 6月24日之後，美光科技股可能會走向拋物線。原因如下。"
      },
      {
        "uuid": "5cac9f7a-4b34-3d79-bc83-059016fdf1ae",
        "title": "Is It Too Late To Consider AMD (AMD) After Its 301% One Year Surge?",
        "publisher": "Simply Wall St.",
        "link": "https://finance.yahoo.com/markets/stocks/articles/too-consider-amd-amd-301-100622705.html",
        "providerPublishTime": 1780826782,
        "type": "STORY",
        "thumbnail": {
          "resolutions": [
            {
              "url": "https://s.yimg.com/uu/api/res/1.2/qQQ8mpCpMuvTPXTeKADXJQ--~B/aD00MzI7dz0xMTk0O2FwcGlkPXl0YWNoeW9u/https://media.zenfs.com/en/simply_wall_st__316/a882d53b581ebe737458ea1484ce4133",
              "width": 1194,
              "height": 432,
              "tag": "original"
            },
            {
              "url": "https://s.yimg.com/uu/api/res/1.2/s22m4gTvBzH.4N9qkkNqSw--~B/Zmk9ZmlsbDtoPTE0MDtweW9mZj0wO3c9MTQwO2FwcGlkPXl0YWNoeW9u/https://media.zenfs.com/en/simply_wall_st__316/a882d53b581ebe737458ea1484ce4133",
              "width": 140,
              "height": 140,
              "tag": "140x140"
            }
          ]
        },
        "relatedTickers": [
          "AMD"
        ],
        "_sym": "AMD",
        "titleZh": "在AMD （ AMD ）一年激增301 ％後，考慮是否爲時已晚？"
      },
      {
        "uuid": "dabafa87-9ea8-351c-a943-0bd460f965dd",
        "title": "Micron Makes the $1 Trillion Club a Little More Crowded",
        "publisher": "Motley Fool",
        "link": "https://finance.yahoo.com/m/dabafa87-9ea8-351c-a943-0bd460f965dd/micron-makes-the-%241-trillion.html",
        "providerPublishTime": 1780776301,
        "type": "STORY",
        "thumbnail": {
          "resolutions": [
            {
              "url": "https://s.yimg.com/uu/api/res/1.2/gU8wq5KUYbk8LreGiBCELg--~B/aD00NTA7dz04MDA7YXBwaWQ9eXRhY2h5b24-/https://media.zenfs.com/en/motleyfool.com/c9a8416ce677c722cbe72883c22fb3ec",
              "width": 800,
              "height": 450,
              "tag": "original"
            },
            {
              "url": "https://s.yimg.com/uu/api/res/1.2/rliE.XkhE9Pvh_oq8GI71A--~B/Zmk9ZmlsbDtoPTE0MDtweW9mZj0wO3c9MTQwO2FwcGlkPXl0YWNoeW9u/https://media.zenfs.com/en/motleyfool.com/c9a8416ce677c722cbe72883c22fb3ec",
              "width": 140,
              "height": 140,
              "tag": "140x140"
            }
          ]
        },
        "relatedTickers": [
          "MU",
          "NVDA",
          "LLY"
        ],
        "_sym": "MU",
        "titleZh": "美光讓$ 1兆俱樂部更加擁擠"
      },
      {
        "uuid": "e8ac007d-5cd6-37b2-bba1-5de314303ab9",
        "title": "Fed official shines a light on looming AI moment in 2027",
        "publisher": "TheStreet",
        "link": "https://finance.yahoo.com/m/e8ac007d-5cd6-37b2-bba1-5de314303ab9/fed-official-shines-a-light.html",
        "providerPublishTime": 1780773180,
        "type": "STORY",
        "thumbnail": {
          "resolutions": [
            {
              "url": "https://s.yimg.com/uu/api/res/1.2/Ec0I3kXQ4lhmyLmWjr8ttQ--~B/aD02NzU7dz0xMjAwO2FwcGlkPXl0YWNoeW9u/https://media.zenfs.com/en/thestreet_881/cda34099f492f852e1750d5ea73e396d",
              "width": 1200,
              "height": 675,
              "tag": "original"
            },
            {
              "url": "https://s.yimg.com/uu/api/res/1.2/rcS_J7wBNKNix5fUN2UD4g--~B/Zmk9ZmlsbDtoPTE0MDtweW9mZj0wO3c9MTQwO2FwcGlkPXl0YWNoeW9u/https://media.zenfs.com/en/thestreet_881/cda34099f492f852e1750d5ea73e396d",
              "width": 140,
              "height": 140,
              "tag": "140x140"
            }
          ]
        },
        "relatedTickers": [
          "MU",
          "NVDA"
        ],
        "_sym": "MU",
        "titleZh": "聯儲局官員揭示了2027年即將到來的人工智能時刻"
      },
      {
        "uuid": "adb20634-b3e6-3c74-9f4f-c9f0ea6f4bef",
        "title": "AI Chip Stocks Sold Off This Week. Is AMD a Buying Opportunity or a Falling Knife?",
        "publisher": "Motley Fool",
        "link": "https://finance.yahoo.com/m/adb20634-b3e6-3c74-9f4f-c9f0ea6f4bef/ai-chip-stocks-sold-off-this.html",
        "providerPublishTime": 1780773120,
        "type": "STORY",
        "thumbnail": {
          "resolutions": [
            {
              "url": "https://s.yimg.com/uu/api/res/1.2/i7zMdQROl_voR3T4oqOu3A--~B/aD0xMDQ5O3c9MTQwMDthcHBpZD15dGFjaHlvbg--/https://media.zenfs.com/en/motleyfool.com/e2cc2e2069b32bd8ed2ffbe706820e82",
              "width": 1400,
              "height": 1049,
              "tag": "original"
            },
            {
              "url": "https://s.yimg.com/uu/api/res/1.2/yyx_3G5OXv86A3oa.W7EEA--~B/Zmk9ZmlsbDtoPTE0MDtweW9mZj0wO3c9MTQwO2FwcGlkPXl0YWNoeW9u/https://media.zenfs.com/en/motleyfool.com/e2cc2e2069b32bd8ed2ffbe706820e82",
              "width": 140,
              "height": 140,
              "tag": "140x140"
            }
          ]
        },
        "relatedTickers": [
          "NVDA",
          "AMD",
          "AVGO"
        ],
        "_sym": "AMD",
        "titleZh": "人工智能芯片股本周售罄。AMD是購買機會還是落刀？"
      },
      {
        "uuid": "4c1b119e-05b4-3c1b-8366-04d86516418f",
        "title": "TD Cowen Raises PT on Advanced Micro Devices (AMD) Stock",
        "publisher": "Insider Monkey",
        "link": "https://finance.yahoo.com/markets/stocks/articles/td-cowen-raises-pt-advanced-172502621.html",
        "providerPublishTime": 1780766702,
        "type": "STORY",
        "thumbnail": {
          "resolutions": [
            {
              "url": "https://s.yimg.com/uu/api/res/1.2/iPzbsf88PibqKOmALEG5PA--~B/aD04MTY7dz0xNDU2O2FwcGlkPXl0YWNoeW9u/https://media.zenfs.com/en/insidermonkey.com/78ee81d4d8cbe53924c848faf9b29aa4",
              "width": 1456,
              "height": 816,
              "tag": "original"
            },
            {
              "url": "https://s.yimg.com/uu/api/res/1.2/grnQ9Qh4kyp7BsKLa38G1A--~B/Zmk9ZmlsbDtoPTE0MDtweW9mZj0wO3c9MTQwO2FwcGlkPXl0YWNoeW9u/https://media.zenfs.com/en/insidermonkey.com/78ee81d4d8cbe53924c848faf9b29aa4",
              "width": 140,
              "height": 140,
              "tag": "140x140"
            }
          ]
        },
        "relatedTickers": [
          "AMD"
        ],
        "_sym": "AMD",
        "titleZh": "TD Cowen提高了Advanced Micro Devices (AMD)股票的PT"
      },
      {
        "uuid": "1b1e7a4e-40ea-38ac-a0e7-162e928e64fe",
        "title": "Is NVIDIA (NVDA) One of the Best Big Company Stocks to Buy Right Now?",
        "publisher": "Insider Monkey",
        "link": "https://finance.yahoo.com/markets/stocks/articles/nvidia-nvda-one-best-big-172431089.html",
        "providerPublishTime": 1780766671,
        "type": "STORY",
        "thumbnail": {
          "resolutions": [
            {
              "url": "https://s.yimg.com/uu/api/res/1.2/TTeuFy5Yw2gv7xivFvRsTg--~B/aD04MTY7dz0xNDU2O2FwcGlkPXl0YWNoeW9u/https://media.zenfs.com/en/insidermonkey.com/aa94e059977d3251b8b0630718e013fc",
              "width": 1456,
              "height": 816,
              "tag": "original"
            },
            {
              "url": "https://s.yimg.com/uu/api/res/1.2/TZeknJ_fhN5h4AGoB8ZDOg--~B/Zmk9ZmlsbDtoPTE0MDtweW9mZj0wO3c9MTQwO2FwcGlkPXl0YWNoeW9u/https://media.zenfs.com/en/insidermonkey.com/aa94e059977d3251b8b0630718e013fc",
              "width": 140,
              "height": 140,
              "tag": "140x140"
            }
          ]
        },
        "relatedTickers": [
          "NVDA",
          "COHR",
          "MRVL"
        ],
        "_sym": "COHR",
        "titleZh": "NVIDIA (NVDA)是目前最值得購買的大公司股票之一嗎？"
      },
      {
        "uuid": "cf6d9fbb-cdd9-3b2f-9e39-0c6149e4ee02",
        "title": "Analyst See More Upside Despite Micron Technology’s (MU) 90% Gains in May",
        "publisher": "Insider Monkey",
        "link": "https://finance.yahoo.com/markets/stocks/articles/analyst-see-more-upside-despite-171738561.html",
        "providerPublishTime": 1780766258,
        "type": "STORY",
        "thumbnail": {
          "resolutions": [
            {
              "url": "https://s.yimg.com/uu/api/res/1.2/WV1rZpZVZ5.vOErnVRlVLA--~B/aD04MTY7dz0xNDU2O2FwcGlkPXl0YWNoeW9u/https://media.zenfs.com/en/insidermonkey.com/cece14d8df3ff9750f89999715c2f4bb",
              "width": 1456,
              "height": 816,
              "tag": "original"
            },
            {
              "url": "https://s.yimg.com/uu/api/res/1.2/4kPN3dT4i0V14HKxSh4WGg--~B/Zmk9ZmlsbDtoPTE0MDtweW9mZj0wO3c9MTQwO2FwcGlkPXl0YWNoeW9u/https://media.zenfs.com/en/insidermonkey.com/cece14d8df3ff9750f89999715c2f4bb",
              "width": 140,
              "height": 140,
              "tag": "140x140"
            }
          ]
        },
        "relatedTickers": [
          "MU"
        ],
        "_sym": "MU",
        "titleZh": "分析師認為，儘管美光科技（ MU ）在5月份獲得了90 ％的收益，但還是有更多的上行空間"
      }
    ],
    "fetched_at": 1780845632111
  }
}